mimid/__init__.py
mimid/api.py
mimid/common.py
mimid/configuration.py
mimid/exceptions.py
mimid/verification.py
mimid/matchers/__init__.py
mimid/matchers/call.py
mimid/matchers/value.py
mimid-0.0.10.dist-info/LICENSE
mimid-0.0.10.dist-info/METADATA
mimid-0.0.10.dist-info/WHEEL
mimid-0.0.10.dist-info/top_level.txt
mimid-0.0.10.dist-info/RECORD
