Metadata-Version: 2.1
Name: mimid
Version: 0.0.10
Summary: Modern mocking library for Python.
Home-page: https://github.com/konradhalas/mimid
Author: Konrad Hałas
Author-email: halas.konrad@gmail.com
License: MIT
Keywords: testing mocking
Classifier: Development Status :: 1 - Planning
Classifier: Intended Audience :: Developers
Classifier: License :: OSI Approved :: MIT License
Classifier: Operating System :: OS Independent
Classifier: Programming Language :: Python
Classifier: Programming Language :: Python :: 3.6
Classifier: Programming Language :: Python :: 3.7
Classifier: Programming Language :: Python :: 3.8
Classifier: Programming Language :: Python :: 3.9
Classifier: Topic :: Software Development :: Libraries :: Python Modules
Classifier: Topic :: Software Development :: Testing
Classifier: Topic :: Software Development :: Testing :: Mocking
Requires-Python: >=3.6
License-File: LICENSE
Provides-Extra: dev
Requires-Dist: pytest (>=4) ; extra == 'dev'
Requires-Dist: pytest-cov ; extra == 'dev'
Requires-Dist: coveralls ; extra == 'dev'
Requires-Dist: black ; extra == 'dev'
Requires-Dist: mypy ; extra == 'dev'
Requires-Dist: pylint ; extra == 'dev'
